{
  "id": "fe1569e5",
  "documentId": "Understanding Arguments_ An Introduction to Informal Logic (1)",
  "content": "ghtweight. This exam-\nple illustrates a common problem and its solution. A term that works perfectly\n\n\n\n319\nVAGUENESS\nwell in one area becomes vague when applied in some other (usually more\nspecialized)  area.  This  vagueness  can  then  be  removed  by  adopting  more\nprecise rules in the problematic area. Vagueness is resolved by definition.\nFor each of the following terms, give one case to which the term clearly ap-\nplies, one case to which the term clearly does not apply, and one borderline",
  "index": 2184,
  "metadata": {
    "title": "Understanding",
    "pageCount": 577,
    "pdfInfo": {
      "PDFFormatVersion": "1.5",
      "IsAcroFormPresent": false,
      "IsXFAPresent": false,
      "Title": "Cengage Advantage Books: Understanding Arguments: An Introduction to Informal Logic",
      "Author": "Walter Sinnott-Armstrong",
      "Creator": "Adobe InDesign CS2 (4.0.5)",
      "Producer": "Acrobat Distiller 6.0 (Windows)",
      "CreationDate": "D:20020101054654+05'30'",
      "ModDate": "D:20100730084856+05'30'"
    },
    "pdfMetadata": {
      "_metadata": {
        "pdfx:universalↂ0020pdf": "The process that creates this PDF constitutes a trade secret of codeMantra, LLC and is protected by the copyright laws of the United States",
        "dc:title": "9781439064139.pdf",
        "dc:creator": ""
      }
    },
    "pdfVersion": "unknown",
    "extractedAt": "2025-04-27T16:02:01.111Z",
    "author": "the copyright herein may be reproduced",
    "date": "the 1976",
    "documentId": "Understanding Arguments_ An Introduction to Informal Logic (1)",
    "chunkIndex": 2184,
    "chunkId": "fe1569e5",
    "isFirstChunk": false,
    "isLastChunk": false
  }
}