{
  "id": "a6b4d2a6",
  "documentId": "Understanding Arguments_ An Introduction to Informal Logic (1)",
  "content": "ch nothing exists, ac-\ncording to the proposition we are diagramming. If all squares are rectangles,\n\n\n\n181\nCategorical Propositions\nSquaresRectangles123\nAliensSpies123\nTrianglesSquares123\nEither method of representation seems plausible. Perhaps the first seems more\nnatural.  We  shall,  however,  use  the  system  of  overlapping  circles,  because\nthey  will  work  better  when  we  get  to  more  complex  arguments.  They  are\ncalled Venn  diagrams,after  their  inventor,  John  Venn,  a  nin",
  "index": 1250,
  "metadata": {
    "title": "Understanding",
    "pageCount": 577,
    "pdfInfo": {
      "PDFFormatVersion": "1.5",
      "IsAcroFormPresent": false,
      "IsXFAPresent": false,
      "Title": "Cengage Advantage Books: Understanding Arguments: An Introduction to Informal Logic",
      "Author": "Walter Sinnott-Armstrong",
      "Creator": "Adobe InDesign CS2 (4.0.5)",
      "Producer": "Acrobat Distiller 6.0 (Windows)",
      "CreationDate": "D:20020101054654+05'30'",
      "ModDate": "D:20100730084856+05'30'"
    },
    "pdfMetadata": {
      "_metadata": {
        "pdfx:universalↂ0020pdf": "The process that creates this PDF constitutes a trade secret of codeMantra, LLC and is protected by the copyright laws of the United States",
        "dc:title": "9781439064139.pdf",
        "dc:creator": ""
      }
    },
    "pdfVersion": "unknown",
    "extractedAt": "2025-04-27T16:16:46.747Z",
    "author": "the copyright herein may be reproduced",
    "date": "the 1976",
    "documentId": "Understanding Arguments_ An Introduction to Informal Logic (1)",
    "chunkIndex": 1250,
    "chunkId": "a6b4d2a6",
    "isFirstChunk": false,
    "isLastChunk": false
  }
}