{
  "id": "155b5314",
  "documentId": "Understanding Arguments_ An Introduction to Informal Logic (1)",
  "content": "king. (F, L, G) (This example comes from Charles L. Stevenson.)\n1.  If “~punless q” is translated as “p)q,” then “punless q” can be translated\nas “p q.” Why?\n2.  Symbolize the following argument and give its form. Does this example\nshow that modus ponensis not always valid? Why or why not?\nOpinion polls taken just before the 1980 election showed the Republican Ronald\nReagan decisively ahead of the Democrat Jimmy Carter, with the other Republican\nin the race, John Anderson, a distant third. Those",
  "index": 1228,
  "metadata": {
    "title": "Understanding",
    "pageCount": 577,
    "pdfInfo": {
      "PDFFormatVersion": "1.5",
      "IsAcroFormPresent": false,
      "IsXFAPresent": false,
      "Title": "Cengage Advantage Books: Understanding Arguments: An Introduction to Informal Logic",
      "Author": "Walter Sinnott-Armstrong",
      "Creator": "Adobe InDesign CS2 (4.0.5)",
      "Producer": "Acrobat Distiller 6.0 (Windows)",
      "CreationDate": "D:20020101054654+05'30'",
      "ModDate": "D:20100730084856+05'30'"
    },
    "pdfMetadata": {
      "_metadata": {
        "pdfx:universalↂ0020pdf": "The process that creates this PDF constitutes a trade secret of codeMantra, LLC and is protected by the copyright laws of the United States",
        "dc:title": "9781439064139.pdf",
        "dc:creator": ""
      }
    },
    "pdfVersion": "unknown",
    "extractedAt": "2025-04-27T16:02:04.273Z",
    "author": "the copyright herein may be reproduced",
    "date": "the 1976",
    "documentId": "Understanding Arguments_ An Introduction to Informal Logic (1)",
    "chunkIndex": 1228,
    "chunkId": "155b5314",
    "isFirstChunk": false,
    "isLastChunk": false
  }
}