{
  "id": "817ceed4",
  "documentId": "Understanding Arguments_ An Introduction to Informal Logic (1)",
  "content": " an exception for a pregnancy due\nto rape? Certainly. They can say that persons have a right to life only if they\ndidn’t come into existence because of rape; or they can say that all persons\nhave a right to life, but that some have less of a right to life than others, in par-\nticular, that those who came into existence because of rape have less. But these\nstatements have a rather unpleasant sound. Surely the question of whether\nyou have a right to life at all, or how much of it you have, shouldn",
  "index": 3149,
  "metadata": {
    "title": "Understanding",
    "pageCount": 577,
    "pdfInfo": {
      "PDFFormatVersion": "1.5",
      "IsAcroFormPresent": false,
      "IsXFAPresent": false,
      "Title": "Cengage Advantage Books: Understanding Arguments: An Introduction to Informal Logic",
      "Author": "Walter Sinnott-Armstrong",
      "Creator": "Adobe InDesign CS2 (4.0.5)",
      "Producer": "Acrobat Distiller 6.0 (Windows)",
      "CreationDate": "D:20020101054654+05'30'",
      "ModDate": "D:20100730084856+05'30'"
    },
    "pdfMetadata": {
      "_metadata": {
        "pdfx:universalↂ0020pdf": "The process that creates this PDF constitutes a trade secret of codeMantra, LLC and is protected by the copyright laws of the United States",
        "dc:title": "9781439064139.pdf",
        "dc:creator": ""
      }
    },
    "pdfVersion": "unknown",
    "extractedAt": "2025-04-27T16:02:04.273Z",
    "author": "the copyright herein may be reproduced",
    "date": "the 1976",
    "documentId": "Understanding Arguments_ An Introduction to Informal Logic (1)",
    "chunkIndex": 3149,
    "chunkId": "817ceed4",
    "isFirstChunk": false,
    "isLastChunk": false
  }
}