{
  "id": "78f3a23f",
  "documentId": "Understanding Arguments_ An Introduction to Informal Logic (1)",
  "content": "lain and evaluate the following response to critics of college\nrestrictions on hate speech:\n[Defenders of such restrictions] will ask whether an educational institution does not\nhave the power...to enact reasonable regulations aimed at assuring equal person-\nhood on campus. If one characterizes the issue this way,...a different set of slopes\nwill look slippery. If we do not intervene to protect equality here, what will the next\noutrage be?3\n3.  When John Stewart interviewed William Bennett (form",
  "index": 2270,
  "metadata": {
    "title": "Understanding",
    "pageCount": 577,
    "pdfInfo": {
      "PDFFormatVersion": "1.5",
      "IsAcroFormPresent": false,
      "IsXFAPresent": false,
      "Title": "Cengage Advantage Books: Understanding Arguments: An Introduction to Informal Logic",
      "Author": "Walter Sinnott-Armstrong",
      "Creator": "Adobe InDesign CS2 (4.0.5)",
      "Producer": "Acrobat Distiller 6.0 (Windows)",
      "CreationDate": "D:20020101054654+05'30'",
      "ModDate": "D:20100730084856+05'30'"
    },
    "pdfMetadata": {
      "_metadata": {
        "pdfx:universalↂ0020pdf": "The process that creates this PDF constitutes a trade secret of codeMantra, LLC and is protected by the copyright laws of the United States",
        "dc:title": "9781439064139.pdf",
        "dc:creator": ""
      }
    },
    "pdfVersion": "unknown",
    "extractedAt": "2025-04-27T16:06:43.256Z",
    "author": "the copyright herein may be reproduced",
    "date": "the 1976",
    "documentId": "Understanding Arguments_ An Introduction to Informal Logic (1)",
    "chunkIndex": 2270,
    "chunkId": "78f3a23f",
    "isFirstChunk": false,
    "isLastChunk": false
  }
}