{
  "id": "5b26078b",
  "documentId": "Understanding Arguments_ An Introduction to Informal Logic (1)",
  "content": "xpert in the appropriate\nfield, we can still ask whether the question is of the kind that can now be\n\n\n\n362\nCHAPTER 15 ■Fallacies of Relevance\nsettled by an appeal to experts. One sign that a question cannot yet be set-\ntled by experts is that experts in that area do not agree with each other. It\ndoes not do much good to cite one authority in support of a claim if another\nauthority with just as much expertise would endorse the opposite claim.\nMoreover, even the best experts sometimes simply get ",
  "index": 2489,
  "metadata": {
    "title": "Understanding",
    "pageCount": 577,
    "pdfInfo": {
      "PDFFormatVersion": "1.5",
      "IsAcroFormPresent": false,
      "IsXFAPresent": false,
      "Title": "Cengage Advantage Books: Understanding Arguments: An Introduction to Informal Logic",
      "Author": "Walter Sinnott-Armstrong",
      "Creator": "Adobe InDesign CS2 (4.0.5)",
      "Producer": "Acrobat Distiller 6.0 (Windows)",
      "CreationDate": "D:20020101054654+05'30'",
      "ModDate": "D:20100730084856+05'30'"
    },
    "pdfMetadata": {
      "_metadata": {
        "pdfx:universalↂ0020pdf": "The process that creates this PDF constitutes a trade secret of codeMantra, LLC and is protected by the copyright laws of the United States",
        "dc:title": "9781439064139.pdf",
        "dc:creator": ""
      }
    },
    "pdfVersion": "unknown",
    "extractedAt": "2025-04-27T16:16:46.747Z",
    "author": "the copyright herein may be reproduced",
    "date": "the 1976",
    "documentId": "Understanding Arguments_ An Introduction to Informal Logic (1)",
    "chunkIndex": 2489,
    "chunkId": "5b26078b",
    "isFirstChunk": false,
    "isLastChunk": false
  }
}