{
  "id": "31817470",
  "documentId": "Understanding Arguments_ An Introduction to Informal Logic (1)",
  "content": "ural authority for\nthis doctrine is found in the letters of St. Paul (the source of so much that is appalling in tra-\nditional Christian teaching), notably in Romans 3:9–20, 5:12–21, and 1 Corinthians 15:20–22.\nI had thought from something Dr. Craig said later in our debate that this doctrine might be\nrejected in the Wesleyan tradition to which he adheres. But the Articles of Religion of the\nMethodist  Church  (available  at  http://archives.umc.org/interior.asp?ptid=1&mid=1649)\nseem very simila",
  "index": 3728,
  "metadata": {
    "title": "Understanding",
    "pageCount": 577,
    "pdfInfo": {
      "PDFFormatVersion": "1.5",
      "IsAcroFormPresent": false,
      "IsXFAPresent": false,
      "Title": "Cengage Advantage Books: Understanding Arguments: An Introduction to Informal Logic",
      "Author": "Walter Sinnott-Armstrong",
      "Creator": "Adobe InDesign CS2 (4.0.5)",
      "Producer": "Acrobat Distiller 6.0 (Windows)",
      "CreationDate": "D:20020101054654+05'30'",
      "ModDate": "D:20100730084856+05'30'"
    },
    "pdfMetadata": {
      "_metadata": {
        "pdfx:universalↂ0020pdf": "The process that creates this PDF constitutes a trade secret of codeMantra, LLC and is protected by the copyright laws of the United States",
        "dc:title": "9781439064139.pdf",
        "dc:creator": ""
      }
    },
    "pdfVersion": "unknown",
    "extractedAt": "2025-04-27T16:02:06.938Z",
    "author": "the copyright herein may be reproduced",
    "date": "the 1976",
    "documentId": "Understanding Arguments_ An Introduction to Informal Logic (1)",
    "chunkIndex": 3728,
    "chunkId": "31817470",
    "isFirstChunk": false,
    "isLastChunk": false
  }
}