{
  "id": "e590cc3b",
  "documentId": "Understanding Arguments_ An Introduction to Informal Logic (1)",
  "content": "s not to say that all such restrictions are unconstitu-\ntional. It is to say that courts must subject them to the most rigid scrutiny”\n(Korematsu,323 U.S. 214 at 216 [1944]). The Court has never questioned the\nvalidity of those pronouncements. . . .\nPetitioner urges us to adopt for the first time a more restrictive view of\nthe Equal Protection Clause and hold that discrimination against members\nof the white “majority” cannot be suspect if its purpose can be characterized\nas “benign.” The clock o",
  "index": 2894,
  "metadata": {
    "title": "Understanding",
    "pageCount": 577,
    "pdfInfo": {
      "PDFFormatVersion": "1.5",
      "IsAcroFormPresent": false,
      "IsXFAPresent": false,
      "Title": "Cengage Advantage Books: Understanding Arguments: An Introduction to Informal Logic",
      "Author": "Walter Sinnott-Armstrong",
      "Creator": "Adobe InDesign CS2 (4.0.5)",
      "Producer": "Acrobat Distiller 6.0 (Windows)",
      "CreationDate": "D:20020101054654+05'30'",
      "ModDate": "D:20100730084856+05'30'"
    },
    "pdfMetadata": {
      "_metadata": {
        "pdfx:universalↂ0020pdf": "The process that creates this PDF constitutes a trade secret of codeMantra, LLC and is protected by the copyright laws of the United States",
        "dc:title": "9781439064139.pdf",
        "dc:creator": ""
      }
    },
    "pdfVersion": "unknown",
    "extractedAt": "2025-04-27T16:06:43.256Z",
    "author": "the copyright herein may be reproduced",
    "date": "the 1976",
    "documentId": "Understanding Arguments_ An Introduction to Informal Logic (1)",
    "chunkIndex": 2894,
    "chunkId": "e590cc3b",
    "isFirstChunk": false,
    "isLastChunk": false
  }
}