{
  "id": "c7b6262d",
  "documentId": "Understanding Arguments_ An Introduction to Informal Logic (1)",
  "content": "to simplify, when people are infected by a particular organism, they\noften develop antibodies that are specifically aimed at this organism. In\nthe case of Legionnaires’ disease, these antibodies were easier to detect\nthan the bacterium itself. They also remained in the patients’ bodies after\nthe infection had run its course. We thus have another chance to apply the\nNCT:  If  Legionnaires’  disease  was  caused  by  this  particular  bacterium,\nthen whenever the disease was present, this antibody",
  "index": 1672,
  "metadata": {
    "title": "Understanding",
    "pageCount": 577,
    "pdfInfo": {
      "PDFFormatVersion": "1.5",
      "IsAcroFormPresent": false,
      "IsXFAPresent": false,
      "Title": "Cengage Advantage Books: Understanding Arguments: An Introduction to Informal Logic",
      "Author": "Walter Sinnott-Armstrong",
      "Creator": "Adobe InDesign CS2 (4.0.5)",
      "Producer": "Acrobat Distiller 6.0 (Windows)",
      "CreationDate": "D:20020101054654+05'30'",
      "ModDate": "D:20100730084856+05'30'"
    },
    "pdfMetadata": {
      "_metadata": {
        "pdfx:universalↂ0020pdf": "The process that creates this PDF constitutes a trade secret of codeMantra, LLC and is protected by the copyright laws of the United States",
        "dc:title": "9781439064139.pdf",
        "dc:creator": ""
      }
    },
    "pdfVersion": "unknown",
    "extractedAt": "2025-04-27T16:06:33.223Z",
    "author": "the copyright herein may be reproduced",
    "date": "the 1976",
    "documentId": "Understanding Arguments_ An Introduction to Informal Logic (1)",
    "chunkIndex": 1672,
    "chunkId": "c7b6262d",
    "isFirstChunk": false,
    "isLastChunk": false
  }
}