{
  "id": "83987032",
  "documentId": "Understanding Arguments_ An Introduction to Informal Logic (1)",
  "content": "sensitive to light can be assembled piecemeal,\nwith the intermediates enjoying some advantage over the competition. Biolo-\ngists have studied organisms that respond to the light that impinges on their\nsurfaces, organisms with indentations of the superficial layer that are able to\nacquire information about the direction of the light, organisms with deeper in-\ndentations whose light detection is more fine grained, organisms that have a\nstructure resembling a pinhole camera, organisms that interpos",
  "index": 3532,
  "metadata": {
    "title": "Understanding",
    "pageCount": 577,
    "pdfInfo": {
      "PDFFormatVersion": "1.5",
      "IsAcroFormPresent": false,
      "IsXFAPresent": false,
      "Title": "Cengage Advantage Books: Understanding Arguments: An Introduction to Informal Logic",
      "Author": "Walter Sinnott-Armstrong",
      "Creator": "Adobe InDesign CS2 (4.0.5)",
      "Producer": "Acrobat Distiller 6.0 (Windows)",
      "CreationDate": "D:20020101054654+05'30'",
      "ModDate": "D:20100730084856+05'30'"
    },
    "pdfMetadata": {
      "_metadata": {
        "pdfx:universalↂ0020pdf": "The process that creates this PDF constitutes a trade secret of codeMantra, LLC and is protected by the copyright laws of the United States",
        "dc:title": "9781439064139.pdf",
        "dc:creator": ""
      }
    },
    "pdfVersion": "unknown",
    "extractedAt": "2025-04-27T16:06:33.223Z",
    "author": "the copyright herein may be reproduced",
    "date": "the 1976",
    "documentId": "Understanding Arguments_ An Introduction to Informal Logic (1)",
    "chunkIndex": 3532,
    "chunkId": "83987032",
    "isFirstChunk": false,
    "isLastChunk": false
  }
}