{
  "id": "02c62998",
  "documentId": "Understanding Arguments_ An Introduction to Informal Logic (1)",
  "content": "ll focus on the simplest kind of immediate inference, which is con-\nversion.We  converta proposition (and produce its converse) simply by revers-\ning the subject term and the predicate term. By the subject term,we mean the\nterm that occurs as the grammatical subject; by the predicate term,we mean\nthe term that occurs as the grammatical predicate. In the A proposition “All\nspies are aliens,” “spies” is the subject term and “aliens” is the predicate\nterm; the converse is “All aliens are spies.”\nIn",
  "index": 1318,
  "metadata": {
    "title": "Understanding",
    "pageCount": 577,
    "pdfInfo": {
      "PDFFormatVersion": "1.5",
      "IsAcroFormPresent": false,
      "IsXFAPresent": false,
      "Title": "Cengage Advantage Books: Understanding Arguments: An Introduction to Informal Logic",
      "Author": "Walter Sinnott-Armstrong",
      "Creator": "Adobe InDesign CS2 (4.0.5)",
      "Producer": "Acrobat Distiller 6.0 (Windows)",
      "CreationDate": "D:20020101054654+05'30'",
      "ModDate": "D:20100730084856+05'30'"
    },
    "pdfMetadata": {
      "_metadata": {
        "pdfx:universalↂ0020pdf": "The process that creates this PDF constitutes a trade secret of codeMantra, LLC and is protected by the copyright laws of the United States",
        "dc:title": "9781439064139.pdf",
        "dc:creator": ""
      }
    },
    "pdfVersion": "unknown",
    "extractedAt": "2025-04-27T16:06:43.256Z",
    "author": "the copyright herein may be reproduced",
    "date": "the 1976",
    "documentId": "Understanding Arguments_ An Introduction to Informal Logic (1)",
    "chunkIndex": 1318,
    "chunkId": "02c62998",
    "isFirstChunk": false,
    "isLastChunk": false
  }
}