{
  "id": "fb5b29c3",
  "documentId": "Understanding Arguments_ An Introduction to Informal Logic (1)",
  "content": "I invite you in.” \nBut it might be argued that there are other ways one can have acquired a\nright to the use of another person’s body than by having been invited to use\nit  by  that  person.  Suppose  a  woman  voluntarily  indulges  in  intercourse,\nknowing of the chance it will issue in pregnancy, and then she does become\npregnant; is she not in part responsible for the presence, in fact the very ex-\nistence of the unborn person inside her? No doubt she did not invite it in.\nBut doesn’t her pa",
  "index": 3204,
  "metadata": {
    "title": "Understanding",
    "pageCount": 577,
    "pdfInfo": {
      "PDFFormatVersion": "1.5",
      "IsAcroFormPresent": false,
      "IsXFAPresent": false,
      "Title": "Cengage Advantage Books: Understanding Arguments: An Introduction to Informal Logic",
      "Author": "Walter Sinnott-Armstrong",
      "Creator": "Adobe InDesign CS2 (4.0.5)",
      "Producer": "Acrobat Distiller 6.0 (Windows)",
      "CreationDate": "D:20020101054654+05'30'",
      "ModDate": "D:20100730084856+05'30'"
    },
    "pdfMetadata": {
      "_metadata": {
        "pdfx:universalↂ0020pdf": "The process that creates this PDF constitutes a trade secret of codeMantra, LLC and is protected by the copyright laws of the United States",
        "dc:title": "9781439064139.pdf",
        "dc:creator": ""
      }
    },
    "pdfVersion": "unknown",
    "extractedAt": "2025-04-27T16:06:33.223Z",
    "author": "the copyright herein may be reproduced",
    "date": "the 1976",
    "documentId": "Understanding Arguments_ An Introduction to Informal Logic (1)",
    "chunkIndex": 3204,
    "chunkId": "fb5b29c3",
    "isFirstChunk": false,
    "isLastChunk": false
  }
}